hinhello/__init__.py
hinhello/api.py
hinhello/chs.py
hinhello-0.2.dist-info/LICENSE
hinhello-0.2.dist-info/METADATA
hinhello-0.2.dist-info/WHEEL
hinhello-0.2.dist-info/entry_points.txt
hinhello-0.2.dist-info/top_level.txt
hinhello-0.2.dist-info/RECORD
