Metadata-Version: 2.1
Name: hinhello
Version: 0.2
Summary: You can write hello and hi with specific functions
Home-page: https://github.com/Ceyhunyc/hinhello
Author: Ceyhun
Author-email: coskunyceyhun@gmail.com
License: MIT
Platform: UNKNOWN
